codrsync/__init__.py
codrsync/__main__.py
codrsync/auth.py
codrsync/cli.py
codrsync/cloud_auth.py
codrsync/config.py
codrsync/next_steps.py
codrsync/onboarding.py
codrsync/ai/__init__.py
codrsync/ai/backend.py
codrsync/ai/build.py
codrsync/ai/kickstart.py
codrsync/ai/prp.py
codrsync/cloud/__init__.py
codrsync/cloud/storage.py
codrsync/connect/__init__.py
codrsync/connect/base.py
codrsync/connect/connect.py
codrsync/connect/digitalocean.py
codrsync/connect/github.py
codrsync/connect/mcp.py
codrsync/connect/supabase.py
codrsync/connect/tailwind.py
codrsync/connect/vercel.py
codrsync/i18n/__init__.py
codrsync/i18n/lazy.py
codrsync/i18n/loader.py
codrsync/i18n/strings.py
codrsync/i18n/translator.py
codrsync/local/__init__.py
codrsync/local/export.py
codrsync/local/roadmap.py
codrsync/local/sprint.py
codrsync/local/status.py
codrsync/scanner/__init__.py
codrsync/scanner/context_generator.py
codrsync/scanner/detector.py
codrsync/scanner/doc_scanner.py
codrsync/scanner/github_scanner.py
codrsync/scanner/scan.py
codrsync/utils/__init__.py
codrsync/utils/doctor.py
tests/__init__.py
tests/conftest.py
tests/test_cli.py
tests/test_config.py
tests/test_detector.py
codrsync-1.0.0.dist-info/METADATA
codrsync-1.0.0.dist-info/WHEEL
codrsync-1.0.0.dist-info/entry_points.txt
codrsync-1.0.0.dist-info/top_level.txt
codrsync-1.0.0.dist-info/RECORD
