Metadata-Version: 2.4
Name: codrsync
Version: 1.0.0
Summary: Turn any dev into jedi ninja codr
Author-email: Ciro Arendt <ciro@ciroarendt.com>
License: MIT
Project-URL: Homepage, https://codrsync.dev
Project-URL: Documentation, https://codrsync.dev/docs
Project-URL: Repository, https://github.com/ciroarendt/codrsync
Project-URL: Issues, https://github.com/ciroarendt/codrsync/issues
Keywords: cli,ai,development,orchestrator,claude,prp,codrsync
Classifier: Development Status :: 4 - Beta
Classifier: Environment :: Console
Classifier: Intended Audience :: Developers
Classifier: License :: OSI Approved :: MIT License
Classifier: Operating System :: OS Independent
Classifier: Programming Language :: Python :: 3
Classifier: Programming Language :: Python :: 3.10
Classifier: Programming Language :: Python :: 3.11
Classifier: Programming Language :: Python :: 3.12
Classifier: Programming Language :: Python :: 3.13
Classifier: Topic :: Software Development
Classifier: Topic :: Software Development :: Code Generators
Requires-Python: >=3.10
Requires-Dist: typer>=0.9.0
Requires-Dist: rich>=13.0.0
Requires-Dist: anthropic>=0.18.0
Requires-Dist: pydantic>=2.0.0
Requires-Dist: python-dotenv>=1.0.0
Requires-Dist: openpyxl>=3.1.0
Requires-Dist: questionary>=2.0.0
Provides-Extra: dev
Requires-Dist: pytest>=7.0.0; extra == "dev"
Requires-Dist: pytest-cov>=4.0.0; extra == "dev"
Requires-Dist: black>=23.0.0; extra == "dev"
Requires-Dist: ruff>=0.1.0; extra == "dev"
Requires-Dist: mypy>=1.0.0; extra == "dev"
